wgandiv_pytorch/__init__.py
wgandiv_pytorch/model.py
wgandiv_pytorch/utils.py
wgandiv_pytorch-0.1.2.dist-info/LICENSE.md
wgandiv_pytorch-0.1.2.dist-info/METADATA
wgandiv_pytorch-0.1.2.dist-info/WHEEL
wgandiv_pytorch-0.1.2.dist-info/top_level.txt
wgandiv_pytorch-0.1.2.dist-info/RECORD
