Metadata-Version: 2.1
Name: wgandiv-pytorch
Version: 0.1.2
Summary: In many domains of computer vision, generative adversarial networks (GANs) have achieved great success, among which the fam- ily of Wasserstein GANs (WGANs) is considered to be state-of-the-art due to the theoretical contributions and competitive qualitative performance
Home-page: https://github.com/Lornatang/WassersteinGAN_DIV-PyTorch
Author: Liu Changyu
Author-email: liuchangyu1111@gmail.com
License: Apache
Platform: UNKNOWN
Classifier: License :: OSI Approved :: Apache Software License
Classifier: Programming Language :: Python
Classifier: Programming Language :: Python :: 3
Classifier: Programming Language :: Python :: 3.7
Requires-Python: >=3.5.0
Requires-Dist: torch
